interaxions/__init__.py
interaxions/environments/__init__.py
interaxions/environments/base_environment.py
interaxions/environments/swe_bench/__init__.py
interaxions/environments/swe_bench/env.py
interaxions/hub/__init__.py
interaxions/hub/auto.py
interaxions/hub/constants.py
interaxions/hub/hub_manager.py
interaxions/scaffolds/__init__.py
interaxions/scaffolds/base_scaffold.py
interaxions/scaffolds/swe_agent/__init__.py
interaxions/scaffolds/swe_agent/scaffold.py
interaxions/schemas/__init__.py
interaxions/schemas/environment.py
interaxions/schemas/job.py
interaxions/schemas/models.py
interaxions/schemas/runtime.py
interaxions/schemas/scaffold.py
interaxions/schemas/workflow.py
interaxions/workflows/__init__.py
interaxions/workflows/base_workflow.py
interaxions/workflows/rollout_and_verify/__init__.py
interaxions/workflows/rollout_and_verify/workflow.py
interaxions-0.0.9.dist-info/METADATA
interaxions-0.0.9.dist-info/WHEEL
interaxions-0.0.9.dist-info/licenses/LICENSE
interaxions-0.0.9.dist-info/RECORD
