Metadata-Version: 2.4
Name: interaxions
Version: 0.0.9
Summary: A library for agent and environment protocol interactions
Project-URL: Homepage, https://github.com/Hambaobao/interaxions
Project-URL: Repository, https://github.com/Hambaobao/interaxions
Project-URL: Issues, https://github.com/Hambaobao/interaxions/issues
Author-email: Lei Zhang <jameszhang2880@gmail.com>
License: MIT
License-File: LICENSE
Keywords: agent,environment,interactions,interaxions,protocol
Classifier: Development Status :: 2 - Pre-Alpha
Classifier: Intended Audience :: Developers
Classifier: License :: OSI Approved :: MIT License
Classifier: Programming Language :: Python :: 3
Classifier: Programming Language :: Python :: 3.10
Classifier: Programming Language :: Python :: 3.11
Classifier: Programming Language :: Python :: 3.12
Requires-Python: >=3.10
Requires-Dist: hera>=5.25.1
Requires-Dist: jinja2>=3.0
Requires-Dist: pydantic>=2.0.0
Requires-Dist: pyyaml>=6.0
Provides-Extra: dev
Requires-Dist: datasets>=2.0.0; extra == 'dev'
Requires-Dist: faker>=22.0.0; extra == 'dev'
Requires-Dist: freezegun>=1.4.0; extra == 'dev'
Requires-Dist: ossdata>=0.3.5; extra == 'dev'
Requires-Dist: pytest-cov>=4.1.0; extra == 'dev'
Requires-Dist: pytest-mock>=3.12.0; extra == 'dev'
Requires-Dist: pytest-sugar>=0.9.7; extra == 'dev'
Requires-Dist: pytest-xdist>=3.5.0; extra == 'dev'
Requires-Dist: pytest>=8.0.0; extra == 'dev'
Requires-Dist: yapf>=0.40.0; extra == 'dev'
Provides-Extra: hf
Requires-Dist: datasets>=2.0.0; extra == 'hf'
Provides-Extra: oss
Requires-Dist: ossdata>=0.3.5; extra == 'oss'
